zlw/__init__.py
zlw/_version.py
zlw/corrections.py
zlw/kernels.py
zlw/window.py
zlw/bin/__init__.py
zlw/bin/sim_analytic.py
zlw/bin/sim_catalog.py
zlw/bin/sim_psd.py
zlw/bin/sim_skymap.py
zlw/examples/__init__.py
zlw/examples/example_O3_psd.py
zlw/examples/example_causal_windowing.py
zlw-0.2.1.dist-info/licenses/LICENSE
zlw-0.2.1.dist-info/METADATA
zlw-0.2.1.dist-info/WHEEL
zlw-0.2.1.dist-info/entry_points.txt
zlw-0.2.1.dist-info/top_level.txt
zlw-0.2.1.dist-info/RECORD
